{"cameraMode":{"drawMode":0,"name":"Shaded","section":"Shading Mode"},"sceneLighting":true,"audioPlay":false,"sceneViewState":{"m_AlwaysRefresh":false,"showFog":true,"showSkybox":true,"showFlares":true,"showImageEffects":true,"showParticleSystems":true,"showVisualEffectGraphs":true,"m_FxEnabled":true},"in2DMode":false,"pivot":{"x":79.53285217285156,"y":25.192581176757814,"z":49.02584457397461},"rotation":{"x":0.1591435670852661,"y":0.585703432559967,"z":-0.1186118870973587,"w":0.7858479619026184},"size":2.0531671047210695,"orthographic":false}